proxipy/__init__.py
proxipy/__version__.py
proxipy/proxipy.py
proxipy-1.1.dist-info/METADATA
proxipy-1.1.dist-info/RECORD
proxipy-1.1.dist-info/WHEEL
proxipy-1.1.dist-info/top_level.txt
