Metadata-Version: 2.1
Name: proxipy
Version: 1.1
Summary: Need proxy? Catch it.
Home-page: http://github.com/sttlr/proxipy
Author: sttlr
License: MIT
Platform: UNKNOWN
Classifier: License :: OSI Approved :: MIT License
Classifier: Programming Language :: Python
Classifier: Programming Language :: Python :: 3.5
Classifier: Programming Language :: Python :: 3.7
Classifier: Programming Language :: Python :: Implementation :: CPython
Classifier: Programming Language :: Python :: Implementation :: PyPy
Requires-Python: >=3.5
Requires-Dist: requests (==2.19.1)
Requires-Dist: aiohttp (==3.4.4)
